<item>
  <title>Page with comments</title>
  <link>http://wpthemetestdata.wordpress.com/about/page-with-comments/</link>
  <pubDate>Tue, 04 Sep 2007 17:47:47 +0000</pubDate>
  <dc:creator>themedemos</dc:creator>
  <guid isPermaLink="false">http://wpthemetestdata.wordpress.com/page-with-comments/</guid>
  <description></description>
  <content:encoded><![CDATA[Repository-hosted Themes are required to support display of comments on static Pages as well as on single blog Posts. å This static Page has comments, and these comments should be displayed.



If the Theme includes a custom option to prevent static Pages from displaying comments, such option must be disabled (i.e. so that static Pages display comments) by default.



Also, verify that this Page does not display taxonomy information (e.g. categories or tags) orå time-stampå information (Page publish date/time).]]></content:encoded>
  <excerpt:encoded><![CDATA[]]></excerpt:encoded>
  <wp:post_id>155</wp:post_id>
  <wp:post_date>2007-09-04 10:47:47</wp:post_date>
  <wp:post_date_gmt>2007-09-04 17:47:47</wp:post_date_gmt>
  <wp:comment_status>open</wp:comment_status>
  <wp:ping_status>closed</wp:ping_status>
  <wp:post_name>page-with-comments</wp:post_name>
  <wp:status>publish</wp:status>
  <wp:post_parent>2</wp:post_parent>
  <wp:menu_order>3</wp:menu_order>
  <wp:post_type>page</wp:post_type>
  <wp:post_password></wp:post_password>
  <wp:is_sticky>0</wp:is_sticky>
  <wp:postmeta>
    <wp:meta_key>_wp_page_template</wp:meta_key>
    <wp:meta_value><![CDATA[default]]></wp:meta_value>
  </wp:postmeta>
  <wp:comment>
    <wp:comment_id>167</wp:comment_id>
    <wp:comment_author><![CDATA[Anon]]></wp:comment_author>
    <wp:comment_author_email>anon@example.com</wp:comment_author_email>
    <wp:comment_author_url></wp:comment_author_url>
    <wp:comment_author_IP>59.167.157.3</wp:comment_author_IP>
    <wp:comment_date>2007-09-04 10:49:28</wp:comment_date>
    <wp:comment_date_gmt>2007-09-04 00:49:28</wp:comment_date_gmt>
    <wp:comment_content><![CDATA[Anonymous comment.]]></wp:comment_content>
    <wp:comment_approved>1</wp:comment_approved>
    <wp:comment_type></wp:comment_type>
    <wp:comment_parent>0</wp:comment_parent>
    <wp:comment_user_id>0</wp:comment_user_id>
  </wp:comment>
  <wp:comment>
    <wp:comment_id>168</wp:comment_id>
    <wp:comment_author><![CDATA[tellyworthtest2]]></wp:comment_author>
    <wp:comment_author_email>tellyworth+test2@gmail.com</wp:comment_author_email>
    <wp:comment_author_url></wp:comment_author_url>
    <wp:comment_author_IP>59.167.157.3</wp:comment_author_IP>
    <wp:comment_date>2007-09-04 10:49:03</wp:comment_date>
    <wp:comment_date_gmt>2007-09-04 00:49:03</wp:comment_date_gmt>
    <wp:comment_content><![CDATA[Contributor comment.]]></wp:comment_content>
    <wp:comment_approved>1</wp:comment_approved>
    <wp:comment_type></wp:comment_type>
    <wp:comment_parent>0</wp:comment_parent>
    <wp:comment_user_id>0</wp:comment_user_id>
  </wp:comment>
  <wp:comment>
    <wp:comment_id>169</wp:comment_id>
    <wp:comment_author><![CDATA[Alex Shiels]]></wp:comment_author>
    <wp:comment_author_email>tellyworth@gmail.com</wp:comment_author_email>
    <wp:comment_author_url>http://flightpath.wordpress.com/</wp:comment_author_url>
    <wp:comment_author_IP>59.167.157.3</wp:comment_author_IP>
    <wp:comment_date>2007-09-04 10:48:51</wp:comment_date>
    <wp:comment_date_gmt>2007-09-04 00:48:51</wp:comment_date_gmt>
    <wp:comment_content><![CDATA[Author comment.]]></wp:comment_content>
    <wp:comment_approved>1</wp:comment_approved>
    <wp:comment_type></wp:comment_type>
    <wp:comment_parent>0</wp:comment_parent>
    <wp:comment_user_id>0</wp:comment_user_id>
  </wp:comment>
</item>
